gosdt.cpython-36m-darwin.so
gosdt_deprecated.dylibs/libtbb.12.5.dylib
gosdt_deprecated.dylibs/libtbbmalloc.2.5.dylib
gosdt_deprecated.dylibs/libgmp.10.dylib
gosdt_deprecated-0.0.1.dist-info/RECORD
gosdt_deprecated-0.0.1.dist-info/WHEEL
gosdt_deprecated-0.0.1.dist-info/top_level.txt
gosdt_deprecated-0.0.1.dist-info/METADATA
