Metadata-Version: 2.1
Name: gosdt-deprecated
Version: 0.0.1
Summary: C++ implementation of Generalized Optimal Sparse Decision Trees
Home-page: https://github.com/Jimmy-Lin/GeneralizedOptimalSparseDecisionTrees
Author: Jimmy Lin, Chudi Zhong, and others
Author-email: jimmy.projects.lin@gmail.com
License: UNKNOWN
Platform: UNKNOWN
Classifier: Programming Language :: Python :: 3
Classifier: License :: OSI Approved :: MIT License
Classifier: Operating System :: MacOS
Classifier: Operating System :: POSIX :: Linux
Requires-Python: >=3.6
